CHANGELOG.md
recital/__init__.py
recital/api/__init__.py
recital/api/background_tasks/__init__.py
recital/api/background_tasks/get_bkg_task.py
recital/api/background_tasks/get_bkg_tasks.py
recital/api/background_tasks/post_bkg_task.py
recital/api/background_tasks/put_bkg_task_items.py
recital/api/background_tasks/put_bkg_task_status.py
recital/api/chunks/__init__.py
recital/api/chunks/get_chunks.py
recital/api/chunks/get_chunks_entities.py
recital/api/document_viewer/__init__.py
recital/api/document_viewer/create_document_outline.py
recital/api/document_viewer/get_document_layout.py
recital/api/document_viewer/get_document_layout_file.py
recital/api/document_viewer/get_document_outline.py
recital/api/extract_configuration/__init__.py
recital/api/extract_configuration/get_extract_config.py
recital/api/extract_configuration/put_extract_config.py
recital/api/extract_models/__init__.py
recital/api/extract_models/delete_extract_model.py
recital/api/extract_models/get_extract_model.py
recital/api/extract_models/get_extract_models.py
recital/api/extract_models/post_extract_model.py
recital/api/extract_predictions/__init__.py
recital/api/extract_predictions/post_extract_predictions.py
recital/api/extract_task_results/__init__.py
recital/api/extract_task_results/get_export_task.py
recital/api/extract_task_results/get_extract_result_to_validate.py
recital/api/extract_task_results/get_extract_results.py
recital/api/extract_task_results/validate_extract_result.py
recital/api/extract_tasks/__init__.py
recital/api/extract_tasks/cancel_extract_task.py
recital/api/extract_tasks/delete_extract_task.py
recital/api/extract_tasks/get_extract_task.py
recital/api/extract_tasks/get_extract_task_doc_count.py
recital/api/extract_tasks/get_extract_tasks.py
recital/api/extract_tasks/get_latest_seeds.py
recital/api/extract_tasks/post_extract_task.py
recital/api/extract_tasks/post_synchronous_extract_task.py
recital/api/extract_tasks/put_extract_task_status.py
recital-0.6.0.dist-info/WHEEL
recital-0.6.0.dist-info/METADATA
recital-0.6.0.dist-info/RECORD
