Metadata-Version: 2.1
Name: recital
Version: 0.6.0
Summary: A client library for accessing recital
Author: recital
Author-email: contact@recital.ai
Requires-Python: >=3.6,<4.0
Classifier: Programming Language :: Python :: 3
Classifier: Programming Language :: Python :: 3.6
Classifier: Programming Language :: Python :: 3.7
Classifier: Programming Language :: Python :: 3.8
Requires-Dist: attrs (>=20.1.0,<21.0.0)
Requires-Dist: httpx (>=0.15.4,<0.18.0)
Requires-Dist: python-dateutil (>=2.8.0,<3.0.0)
